{"ParsedResults":[{"TextOverlay":{"Lines":[{"LineText":"036620 TKW","Words":[{"WordText":"036620","Left":8.3333330154418945,"Top":433.33331298828125,"Height":577.5,"Width":1749.9998779296875},{"WordText":"TKW","Left":1708.333251953125,"Top":525.83331298828125,"Height":208.33332824707031,"Width":391.66665649414062}],"MaxHeight":590.0,"MinTop":433.33331298828125},{"LineText":"h","Words":[{"WordText":"h","Left":2225.833251953125,"Top":541.6666259765625,"Height":194.99998474121094,"Width":83.333328247070312}],"MaxHeight":194.99998474121094,"MinTop":541.6666259765625},{"LineText":"BP","Words":[{"WordText":"BP","Left":1837.4998779296875,"Top":1023.3333129882812,"Height":145.0,"Width":200.83332824707031}],"MaxHeight":145.0,"MinTop":1023.3333129882812}],"HasOverlay":true,"Message":"Total lines: 3"},"TextOrientation":"0","FileParseExitCode":1,"ParsedText":"036620 TKW\th\t\r\nBP\t\r\n","ErrorMessage":"","ErrorDetails":""}],"OCRExitCode":1,"IsErroredOnProcessing":false,"ProcessingTimeInMilliseconds":"692"}