[
  {
    "locale": "en",
    "description": "Genus\nCELLLLLLLLLLLL 3335AA\n0022402\n0CUM KW\n",
    "boundingPoly": {
      "vertices": [
        {
          "x": 216,
          "y": -8
        },
        {
          "x": 2130,
          "y": -8
        },
        {
          "x": 2130,
          "y": 940
        },
        {
          "x": 216,
          "y": 940
        }
      ]
    }
  },
  {
    "description": "Genus",
    "boundingPoly": {
      "vertices": [
        {
          "x": 664,
          "y": -8
        },
        {
          "x": 1831,
          "y": 22
        },
        {
          "x": 1825,
          "y": 229
        },
        {
          "x": 659,
          "y": 199
        }
      ]
    }
  },
  {
    "description": "CELLLLLLLLLLLL",
    "boundingPoly": {
      "vertices": [
        {
          "x": 220,
          "y": 225
        },
        {
          "x": 1315,
          "y": 266
        },
        {
          "x": 1312,
          "y": 360
        },
        {
          "x": 216,
          "y": 319
        }
      ]
    }
  },
  {
    "description": "3335AA",
    "boundingPoly": {
      "vertices": [
        {
          "x": 1695,
          "y": 280
        },
        {
          "x": 2130,
          "y": 296
        },
        {
          "x": 2126,
          "y": 390
        },
        {
          "x": 1691,
          "y": 374
        }
      ]
    }
  },
  {
    "description": "0022402",
    "boundingPoly": {
      "vertices": [
        {
          "x": 320,
          "y": 464
        },
        {
          "x": 1964,
          "y": 474
        },
        {
          "x": 1962,
          "y": 763
        },
        {
          "x": 318,
          "y": 753
        }
      ]
    }
  },
  {
    "description": "0CUM",
    "boundingPoly": {
      "vertices": [
        {
          "x": 1339,
          "y": 789
        },
        {
          "x": 1830,
          "y": 767
        },
        {
          "x": 1836,
          "y": 918
        },
        {
          "x": 1346,
          "y": 940
        }
      ]
    }
  },
  {
    "description": "KW",
    "boundingPoly": {
      "vertices": [
        {
          "x": 1938,
          "y": 761
        },
        {
          "x": 2110,
          "y": 753
        },
        {
          "x": 2117,
          "y": 905
        },
        {
          "x": 1945,
          "y": 913
        }
      ]
    }
  }
]