[
  {
    "locale": "en",
    "description": "00136440M\nkW\n",
    "boundingPoly": {
      "vertices": [
        {
          "y": 28
        },
        {
          "x": 1059,
          "y": 28
        },
        {
          "x": 1059,
          "y": 287
        },
        {
          "y": 287
        }
      ]
    }
  },
  {
    "description": "00136440M",
    "boundingPoly": {
      "vertices": [
        {
          "x": 13,
          "y": 28
        },
        {
          "x": 1059,
          "y": 104
        },
        {
          "x": 1046,
          "y": 287
        },
        {
          "y": 212
        }
      ]
    }
  },
  {
    "description": "kW",
    "boundingPoly": {
      "vertices": [
        {
          "x": 954,
          "y": 206
        },
        {
          "x": 1059,
          "y": 210
        },
        {
          "x": 1056,
          "y": 277
        },
        {
          "x": 952,
          "y": 273
        }
      ]
    }
  }
]