[{"Confidence":87.976906,"DetectedText":"cenus","Geometry":{"BoundingBox":{"Height":0.105473965,"Left":0.5131283,"Top":0.0013351135,"Width":0.24981245},"Polygon":[{"X":0.5131283,"Y":0.0013351135},{"X":0.76294076,"Y":0.18024032},{"X":0.7381846,"Y":0.28838453},{"X":0.48912227,"Y":0.10680908}]},"Id":0,"ParentId":0,"Type":{"Value":"LINE"}},{"Confidence":79.43632,"DetectedText":"MMYY","Geometry":{"BoundingBox":{"Height":0.08379187,"Left":0.6984246,"Top":0.008010681,"Width":0.15086158},"Polygon":[{"X":0.6984246,"Y":0.008010681},{"X":0.8492862,"Y":0.10913017},{"X":0.83155406,"Y":0.19292203},{"X":0.68069243,"Y":0.091802545}]},"Id":1,"ParentId":0,"Type":{"Value":"LINE"}},{"Confidence":97.8037,"DetectedText":"TH","Geometry":{"BoundingBox":{"Height":0.12725498,"Left":0.08346893,"Top":0.22994389,"Width":0.10291056},"Polygon":[{"X":0.08346893,"Y":0.22994389},{"X":0.18637949,"Y":0.29259256},{"X":0.16192098,"Y":0.41984755},{"X":0.059010416,"Y":0.35719886}]},"Id":2,"ParentId":0,"Type":{"Value":"LINE"}},{"Confidence":63.191105,"DetectedText":"2","Geometry":{"BoundingBox":{"Height":-0.12283044,"Left":0.2835709,"Top":0.23364486,"Width":-0.045011252},"Polygon":[{"X":0.2835709,"Y":0.23364486},{"X":0.23855963,"Y":0.12149533},{"X":0.33458364,"Y":0},{"X":0.3795949,"Y":0.11081442}]},"Id":3,"ParentId":0,"Type":{"Value":"LINE"}},{"Confidence":82.37638,"DetectedText":"64.0 1-1C","Geometry":{"BoundingBox":{"Height":0.27747956,"Left":0.571439,"Top":0.24932267,"Width":0.39484325},"Polygon":[{"X":0.571439,"Y":0.24932267},{"X":0.96628225,"Y":0.47601315},{"X":0.91598517,"Y":0.7534927},{"X":0.5211419,"Y":0.52680224}]},"Id":4,"ParentId":0,"Type":{"Value":"LINE"}},{"Confidence":90.26249,"DetectedText":"kWh","Geometry":{"BoundingBox":{"Height":0.10272027,"Left":0.8207231,"Top":0.6989264,"Width":0.107391655},"Polygon":[{"X":0.8207231,"Y":0.6989264},{"X":0.9281148,"Y":0.7664386},{"X":0.90772694,"Y":0.86915886},{"X":0.8003353,"Y":0.8016467}]},"Id":5,"ParentId":0,"Type":{"Value":"LINE"}},{"Confidence":87.976906,"DetectedText":"cenus","Geometry":{"BoundingBox":{"Height":0.11094158,"Left":0.5131283,"Top":0.0013351135,"Width":0.30726752},"Polygon":[{"X":0.5131283,"Y":0.0013351135},{"X":0.76294076,"Y":0.18024032},{"X":0.7381846,"Y":0.28838453},{"X":0.48912227,"Y":0.10680908}]},"Id":6,"ParentId":0,"Type":{"Value":"WORD"}},{"Confidence":79.43632,"DetectedText":"MMYY","Geometry":{"BoundingBox":{"Height":0.08471245,"Left":0.6984246,"Top":0.008010681,"Width":0.18174931},"Polygon":[{"X":0.6984246,"Y":0.008010681},{"X":0.8492123,"Y":0.10947931},{"X":0.8312078,"Y":0.19225635},{"X":0.6811703,"Y":0.09212283}]},"Id":7,"ParentId":1,"Type":{"Value":"WORD"}},{"Confidence":97.8037,"DetectedText":"TH","Geometry":{"BoundingBox":{"Height":0.12908758,"Left":0.08327082,"Top":0.23097463,"Width":0.11972749},"Polygon":[{"X":0.08327082,"Y":0.23097463},{"X":0.18604651,"Y":0.29238984},{"X":0.16204052,"Y":0.41922563},{"X":0.060015004,"Y":0.3578104}]},"Id":8,"ParentId":2,"Type":{"Value":"WORD"}},{"Confidence":63.191105,"DetectedText":"2","Geometry":{"BoundingBox":{"Height":0.15486033,"Left":0.2835709,"Top":0.23364486,"Width":0.12084507},"Polygon":[{"X":0.2835709,"Y":0.23364486},{"X":0.23855963,"Y":0.12149533},{"X":0.33458364,"Y":0},{"X":0.3795949,"Y":0.11081442}]},"Id":9,"ParentId":3,"Type":{"Value":"WORD"}},{"Confidence":84.26382,"DetectedText":"64.0","Geometry":{"BoundingBox":{"Height":0.27945453,"Left":0.57089275,"Top":0.25233644,"Width":0.44211605},"Polygon":[{"X":0.57089275,"Y":0.25233644},{"X":0.95573896,"Y":0.46995994},{"X":0.9062266,"Y":0.7449933},{"X":0.52213055,"Y":0.5273698}]},"Id":10,"ParentId":4,"Type":{"Value":"WORD"}},{"Confidence":80.488945,"DetectedText":"1-1C","Geometry":{"BoundingBox":{"Height":0.18061197,"Left":0.75543886,"Top":0.41388518,"Width":0.23219208},"Polygon":[{"X":0.75543886,"Y":0.41388518},{"X":0.95648915,"Y":0.53004},{"X":0.92348087,"Y":0.70761013},{"X":0.7231808,"Y":0.59012014}]},"Id":11,"ParentId":4,"Type":{"Value":"WORD"}},{"Confidence":90.26249,"DetectedText":"kWh","Geometry":{"BoundingBox":{"Height":0.10478013,"Left":0.8207052,"Top":0.69959944,"Width":0.12635124},"Polygon":[{"X":0.8207052,"Y":0.69959944},{"X":0.927982,"Y":0.76635516},{"X":0.90772694,"Y":0.86915886},{"X":0.8004501,"Y":0.80106807}]},"Id":12,"ParentId":5,"Type":{"Value":"WORD"}}]