[
  {
    "locale": "en",
    "description": "Property f \"TANGEDCO\"\nac, 3 Phase, 4 Wire Static Watthour Meter\nRO\nKW h\n",
    "boundingPoly": {
      "vertices": [
        {
          "x": 385,
          "y": 76
        },
        {
          "x": 2407,
          "y": 76
        },
        {
          "x": 2407,
          "y": 786
        },
        {
          "x": 385,
          "y": 786
        }
      ]
    }
  },
  {
    "description": "Property",
    "boundingPoly": {
      "vertices": [
        {
          "x": 817,
          "y": 76
        },
        {
          "x": 1295,
          "y": 76
        },
        {
          "x": 1295,
          "y": 207
        },
        {
          "x": 817,
          "y": 207
        }
      ]
    }
  },
  {
    "description": "f",
    "boundingPoly": {
      "vertices": [
        {
          "x": 1404,
          "y": 108
        },
        {
          "x": 1427,
          "y": 108
        },
        {
          "x": 1427,
          "y": 195
        },
        {
          "x": 1404,
          "y": 195
        }
      ]
    }
  },
  {
    "description": "\"TANGEDCO\"",
    "boundingPoly": {
      "vertices": [
        {
          "x": 1480,
          "y": 76
        },
        {
          "x": 2191,
          "y": 76
        },
        {
          "x": 2191,
          "y": 207
        },
        {
          "x": 1480,
          "y": 207
        }
      ]
    }
  },
  {
    "description": "ac,",
    "boundingPoly": {
      "vertices": [
        {
          "x": 521,
          "y": 240
        },
        {
          "x": 741,
          "y": 240
        },
        {
          "x": 741,
          "y": 337
        },
        {
          "x": 521,
          "y": 337
        }
      ]
    }
  },
  {
    "description": "3",
    "boundingPoly": {
      "vertices": [
        {
          "x": 743,
          "y": 240
        },
        {
          "x": 789,
          "y": 240
        },
        {
          "x": 789,
          "y": 337
        },
        {
          "x": 743,
          "y": 337
        }
      ]
    }
  },
  {
    "description": "Phase,",
    "boundingPoly": {
      "vertices": [
        {
          "x": 811,
          "y": 240
        },
        {
          "x": 1133,
          "y": 240
        },
        {
          "x": 1133,
          "y": 337
        },
        {
          "x": 811,
          "y": 337
        }
      ]
    }
  },
  {
    "description": "4",
    "boundingPoly": {
      "vertices": [
        {
          "x": 1156,
          "y": 248
        },
        {
          "x": 1205,
          "y": 248
        },
        {
          "x": 1205,
          "y": 323
        },
        {
          "x": 1156,
          "y": 323
        }
      ]
    }
  },
  {
    "description": "Wire",
    "boundingPoly": {
      "vertices": [
        {
          "x": 1232,
          "y": 248
        },
        {
          "x": 1443,
          "y": 248
        },
        {
          "x": 1443,
          "y": 325
        },
        {
          "x": 1232,
          "y": 325
        }
      ]
    }
  },
  {
    "description": "Static",
    "boundingPoly": {
      "vertices": [
        {
          "x": 1480,
          "y": 246
        },
        {
          "x": 1725,
          "y": 246
        },
        {
          "x": 1725,
          "y": 327
        },
        {
          "x": 1480,
          "y": 327
        }
      ]
    }
  },
  {
    "description": "Watthour",
    "boundingPoly": {
      "vertices": [
        {
          "x": 1775,
          "y": 240
        },
        {
          "x": 2145,
          "y": 240
        },
        {
          "x": 2145,
          "y": 337
        },
        {
          "x": 1775,
          "y": 337
        }
      ]
    }
  },
  {
    "description": "Meter",
    "boundingPoly": {
      "vertices": [
        {
          "x": 2167,
          "y": 240
        },
        {
          "x": 2407,
          "y": 240
        },
        {
          "x": 2407,
          "y": 337
        },
        {
          "x": 2167,
          "y": 337
        }
      ]
    }
  },
  {
    "description": "RO",
    "boundingPoly": {
      "vertices": [
        {
          "x": 388,
          "y": 364
        },
        {
          "x": 683,
          "y": 370
        },
        {
          "x": 680,
          "y": 545
        },
        {
          "x": 385,
          "y": 539
        }
      ]
    }
  },
  {
    "description": "KW",
    "boundingPoly": {
      "vertices": [
        {
          "x": 2092,
          "y": 663
        },
        {
          "x": 2271,
          "y": 657
        },
        {
          "x": 2275,
          "y": 780
        },
        {
          "x": 2096,
          "y": 786
        }
      ]
    }
  },
  {
    "description": "h",
    "boundingPoly": {
      "vertices": [
        {
          "x": 2336,
          "y": 659
        },
        {
          "x": 2383,
          "y": 658
        },
        {
          "x": 2387,
          "y": 772
        },
        {
          "x": 2340,
          "y": 774
        }
      ]
    }
  }
]